{
  "key": "order-bail-rejection",
  "config": {
    "content": [
      {
        "table": {
          "widths": ["*"],
          "body": [
            [
              {
                "stack": [
                  {
                    "text": "In the Court of {{courtName}}, {{courtPlace}}, {{state}}",
                    "style": "header"
                  },
                  {
                    "text": "Case No: {{caseNumber}} of {{caseYear}}",
                    "style": "header"
                  },
                  {
                    "text": "In the matter of: {{caseNumber}}",
                    "style": "header"
                  },
                  {
                    "text": "ORDER",
                    "style": "orderTitle"
                  },
                  {
                    "text": "{{date}}",
                    "style": "date"
                  },
                  {
                    "text": "This matter comes before the Court on the Application for Bail filed by {{applicantName}}, Advocate for {{partyName}}, on {{dateOfApplication}}.",
                    "style": "contentText"
                  },
                  {
                    "text": "WHEREAS, the Court has considered the Application for Bail, which asserts that {{briefSummaryOfBail}}; and",
                    "style": "contentText"
                  },
                  {
                    "text": "WHEREAS, the Court has reviewed the supporting documentation submitted by the Applicant, including",
                    "style": "contentText"
                  },
                  "{{#documentList}}",
                  {
                    "text": "{{documentType}}",
                    "style": "bodyText"
                  },
                  "{{/documentList}}",
                  {
                    "text": "WHEREAS, the Court has taken into account the seriousness of the allegations, the potential risk to public safety, and the likelihood of the Applicant appearing for further proceedings; and",
                    "style": "contentText"
                  },
                  {
                    "text": "WHEREAS, the Court has considered the relevant legal provisions regarding bail;",
                    "style": "contentText"
                  },
                  {
                    "text": "NOW, THEREFORE, IT IS HEREBY ORDERED that:",
                    "style": "contentText"
                  },
                  {
                    "text": "The Application for Bail by {{partyName}} is DENIED. The Applicant shall remain in custody pending further proceedings.",
                    "style": "contentText"
                  },
                  {
                    "text": "IT IS SO ORDERED.",
                    "style": "orderText"
                  },
                  {
                    "text": "{{judgeSignature}}",
                    "style": "signature"
                  },
                  {
                    "text": "{{judgeName}}",
                    "style": "signature"
                  },
                  {
                    "text": "Judge, District {{courtName}}",
                    "style": "signature"
                  },
                  {
                    "text": "{{courtSeal}}",
                    "style": "signature"
                  }
                ],
                "alignment": "left",
                "margin": [0, 20, 0, 20]
              }
            ]
          ]
        },
        "layout": "noBorders"
      }
    ],
    "styles": {
      "header": {
        "fontSize": 14,
        "bold": true,
        "alignment": "center",
        "margin": [0, 0, 0, 5]
      },
      "caseName": {
        "fontSize": 14,
        "alignment": "center",
        "margin": [0, 5, 0, 5]
      },
      "caseNumber": {
        "fontSize": 14,
        "alignment": "center",
        "margin": [0, 5, 0, 5]
      },
      "orderTitle": {
        "fontSize": 16,
        "bold": true,
        "alignment": "center",
        "margin": [0, 5, 0, 5]
      },
      "orderName": {
        "fontSize": 14,
        "bold": true,
        "alignment": "center",
        "margin": [0, 5, 0, 20]
      },
      "date": {
        "fontSize": 12,
        "alignment": "left",
        "margin": [0, 10, 0, 10]
      },
      "contentText": {
        "fontSize": 11,
        "alignment": "left",
        "margin": [0, 10, 0, 10]
      },
      "orderText": {
        "fontSize": 12,
        "bold": true,
        "alignment": "left",
        "margin": [0, 10, 0, 20]
      },
      "signature": {
        "fontSize": 12,
        "alignment": "left",
        "margin": [0, 10, 0, 0]
      },
      "tableData": {
        "bold": true,
        "fontSize": 10,
        "color": "black"
      }
    }
  }
}
